{
    "Pastalar": [],
    "Vok": [],
    "🍩 Shirinliklar": [],
    "Tempura Rollar": [],
    "Zapechoniy Rollar": [],
    "Sushi Rollar": [],
    "🌯 Lavashlar": [
        {
            "photo": "AgACAgIAAxkBAAIOAAFpC3_hhdIQmk39cY7sduzubOJiPgAC8BNrGyeXWUg1n-L1drsotgEAAwIAA3kAAzYE",
            "name": "Tandir Lavash",
            "desc": "Mazli puliga arzidi",
            "price": 33000
        }
    ],
    "🍔 Burger": [],
    "🌮 Donarlar": [],
    "Non Kabob": [],
    "Haggi": [],
    "Xot Dog": [],
    "Klab Sendvich": [],
    "Pide": [],
    "Kfs": [],
    "Qovurilgan Tovuq qanotchalari": [],
    "Salqin Ichimliklar": [],
    "Issiq Ichimliklar": []
}